bitcoin/__init__.py
bitcoin/base58.py
bitcoin/bech32.py
bitcoin/bloom.py
bitcoin/messages.py
bitcoin/net.py
bitcoin/rpc.py
bitcoin/segwit_addr.py
bitcoin/signature.py
bitcoin/signmessage.py
bitcoin/wallet.py
bitcoin/core/__init__.py
bitcoin/core/_bignum.py
bitcoin/core/key.py
bitcoin/core/script.py
bitcoin/core/scripteval.py
bitcoin/core/serialize.py
bitcoin/core/contrib/__init__.py
bitcoin/core/contrib/ripemd160.py
bitcoin/tests/__init__.py
bitcoin/tests/fakebitcoinproxy.py
bitcoin/tests/test_base58.py
bitcoin/tests/test_bech32.py
bitcoin/tests/test_bloom.py
bitcoin/tests/test_checkblock.py
bitcoin/tests/test_core.py
bitcoin/tests/test_fakebitcoinproxy.py
bitcoin/tests/test_key.py
bitcoin/tests/test_messages.py
bitcoin/tests/test_net.py
bitcoin/tests/test_ripemd160.py
bitcoin/tests/test_rpc.py
bitcoin/tests/test_script.py
bitcoin/tests/test_scripteval.py
bitcoin/tests/test_segwit.py
bitcoin/tests/test_serialize.py
bitcoin/tests/test_signmessage.py
bitcoin/tests/test_transactions.py
bitcoin/tests/test_wallet.py
python_bitcoinlib-0.12.2.dist-info/LICENSE
python_bitcoinlib-0.12.2.dist-info/METADATA
python_bitcoinlib-0.12.2.dist-info/WHEEL
python_bitcoinlib-0.12.2.dist-info/top_level.txt
python_bitcoinlib-0.12.2.dist-info/RECORD
