Metadata-Version: 2.1
Name: python-bitcoinlib
Version: 0.12.2
Summary: The Swiss Army Knife of the Bitcoin protocol.
Home-page: https://github.com/petertodd/python-bitcoinlib
License: UNKNOWN
Keywords: bitcoin
Platform: UNKNOWN
Classifier: Programming Language :: Python
Classifier: License :: OSI Approved :: GNU Lesser General Public License v3 or later (LGPLv3+)
